{"stages":[{"id":"6","name":"Tool Install","children":[],"state":"success","type":"STAGE","title":"Tool Install","isSequential":false,"synthetic":true,"placeholder":false,"pauseDurationMillis":0,"totalDurationMillis":159,"startTimeMillis":1780077847364,"agent":"built-in","url":"/job/Pipeline%20Ejemplos%20de%20Stages%20y%20Steps/2/stages/?selected-node=6"},{"id":"14","name":"Deploy de la app a Testing","children":[],"state":"success","type":"STAGE","title":"Deploy de la app a Testing","isSequential":false,"synthetic":false,"placeholder":false,"pauseDurationMillis":0,"totalDurationMillis":348,"startTimeMillis":1780077847666,"agent":"built-in","url":"/job/Pipeline%20Ejemplos%20de%20Stages%20y%20Steps/2/stages/?selected-node=14"},{"id":"26","name":"Ejecución de Unit Tests","children":[],"state":"success","type":"STAGE","title":"Ejecución de Unit Tests","isSequential":false,"synthetic":false,"placeholder":false,"pauseDurationMillis":0,"totalDurationMillis":333,"startTimeMillis":1780077848107,"agent":"built-in","url":"/job/Pipeline%20Ejemplos%20de%20Stages%20y%20Steps/2/stages/?selected-node=26"},{"id":"38","name":"Ejecución de E2E Tests","children":[],"state":"success","type":"STAGE","title":"Ejecución de E2E Tests","isSequential":false,"synthetic":false,"placeholder":false,"pauseDurationMillis":0,"totalDurationMillis":317,"startTimeMillis":1780077848529,"agent":"built-in","url":"/job/Pipeline%20Ejemplos%20de%20Stages%20y%20Steps/2/stages/?selected-node=38"},{"id":"50","name":"Deploy a Prod","children":[],"state":"success","type":"STAGE","title":"Deploy a Prod","isSequential":false,"synthetic":false,"placeholder":false,"pauseDurationMillis":0,"totalDurationMillis":306,"startTimeMillis":1780077848921,"agent":"built-in","url":"/job/Pipeline%20Ejemplos%20de%20Stages%20y%20Steps/2/stages/?selected-node=50"}],"complete":true}